imagesifter/__init__.py
imagesifter/exceptions.py
imagesifter/mains.py
imagesifter/test.py
imagesifter/utils.py
imagesifter-1.0.6.dist-info/DESCRIPTION.rst
imagesifter-1.0.6.dist-info/METADATA
imagesifter-1.0.6.dist-info/RECORD
imagesifter-1.0.6.dist-info/WHEEL
imagesifter-1.0.6.dist-info/metadata.json
imagesifter-1.0.6.dist-info/top_level.txt
