Metadata-Version: 2.0
Name: imagesifter
Version: 1.0.6
Summary: Easy-to-use package for downloading originals of images from web sites 
Home-page: https://github.com/HedonistAnt/ImageSifter
Author: Hedonist_Ant
Author-email: redkandibober666@gmail.com
License: MIT
Keywords: download image web sites
Platform: UNKNOWN
Classifier: Development Status :: 5 - Production/Stable
Classifier: Intended Audience :: Developers
Classifier: License :: OSI Approved :: MIT License
Classifier: Programming Language :: Python :: 2.7
Requires-Python: ~=2.7
